_lzf.cp313-win_arm64.pyd
lzf.py
lzf_python-1.0.5.dist-info/METADATA
lzf_python-1.0.5.dist-info/WHEEL
lzf_python-1.0.5.dist-info/top_level.txt
lzf_python-1.0.5.dist-info/RECORD
